{
  "main": {
    "id": "837a83e40782a750",
    "type": "split",
    "children": [
      {
        "id": "a4bea0205f6ef9b9",
        "type": "tabs",
        "children": [
          {
            "id": "da6b103168ca7403",
            "type": "leaf",
            "state": {
              "type": "markdown",
              "state": {
                "file": "Flius_pj_1/GitHub.md",
                "mode": "source",
                "source": false
              }
            }
          }
        ]
      }
    ],
    "direction": "vertical"
  },
  "left": {
    "id": "03d0fbf351026a3c",
    "type": "split",
    "children": [
      {
        "id": "9e0edd536ee18cd1",
        "type": "tabs",
        "children": [
          {
            "id": "57a898206055ba48",
            "type": "leaf",
            "state": {
              "type": "file-explorer",
              "state": {
                "sortOrder": "alphabetical"
              }
            }
          },
          {
            "id": "6856368e65d2cc79",
            "type": "leaf",
            "state": {
              "type": "search",
              "state": {
                "query": "",
                "matchingCase": false,
                "explainSearch": false,
                "collapseAll": false,
                "extraContext": false,
                "sortOrder": "alphabetical"
              }
            }
          },
          {
            "id": "c61298504100905b",
            "type": "leaf",
            "state": {
              "type": "bookmarks",
              "state": {}
            }
          }
        ]
      }
    ],
    "direction": "horizontal",
    "width": 300
  },
  "right": {
    "id": "735718e3201a59f6",
    "type": "split",
    "children": [
      {
        "id": "ea7385a3ad3808e7",
        "type": "tabs",
        "children": [
          {
            "id": "13b3875a8b4bef8b",
            "type": "leaf",
            "state": {
              "type": "backlink",
              "state": {
                "file": "Flius_pj_1/GitHub.md",
                "collapseAll": false,
                "extraContext": false,
                "sortOrder": "alphabetical",
                "showSearch": false,
                "searchQuery": "",
                "backlinkCollapsed": false,
                "unlinkedCollapsed": true
              }
            }
          },
          {
            "id": "6b731afa30142184",
            "type": "leaf",
            "state": {
              "type": "outgoing-link",
              "state": {
                "file": "Flius_pj_1/GitHub.md",
                "linksCollapsed": false,
                "unlinkedCollapsed": true
              }
            }
          },
          {
            "id": "e911a59a4c19f51f",
            "type": "leaf",
            "state": {
              "type": "tag",
              "state": {
                "sortOrder": "frequency",
                "useHierarchy": true
              }
            }
          },
          {
            "id": "b62c781e8a85fc62",
            "type": "leaf",
            "state": {
              "type": "outline",
              "state": {
                "file": "Flius_pj_1/GitHub.md"
              }
            }
          }
        ]
      }
    ],
    "direction": "horizontal",
    "width": 300,
    "collapsed": true
  },
  "left-ribbon": {
    "hiddenItems": {
      "switcher:퀵 스위처 열기": false,
      "graph:그래프 뷰 열기": false,
      "canvas:새 캔버스 만들기": false,
      "daily-notes:오늘의 데일리 노트 열기": false,
      "templates:템플릿 삽입": false,
      "command-palette:명령어 팔레트 열기": false
    }
  },
  "active": "da6b103168ca7403",
  "lastOpenFiles": [
    "image_file/Pasted image 20240310230858.png",
    "image_file/Pasted image 20240310230856.png",
    "Flius_pj_1/CSS.md",
    "Flius_pj_1/HTML.md",
    "Flius_pj_1/Architecture.md"
  ]
}